{
  "id": "p2_n4_b5_v19",
  "title": "\\{p2_n4_b5_v19\\}",
  "sections": [
    {
      "title": "\\{p2_n4_b5_v19_s1\\}",
      "id": "p2_n4_b5_v19_s1",
      "paragraphs": [
        {
          "number": "181",
          "content": "\\{p2_n4_b5_v19_s1_p1\\}",
          "id": "p2_n4_b5_v19_s1_p1"
        }
      ],
      "endingText": null
    },
    {
      "title": "\\{p2_n4_b5_v19_s2\\}",
      "id": "p2_n4_b5_v19_s2",
      "paragraphs": [
        {
          "number": "182",
          "content": "\\{p2_n4_b5_v19_s2_p1\\}",
          "id": "p2_n4_b5_v19_s2_p1"
        }
      ],
      "endingText": null
    },
    {
      "title": "\\{p2_n4_b5_v19_s3\\}",
      "id": "p2_n4_b5_v19_s3",
      "paragraphs": [
        {
          "number": "183",
          "content": "\\{p2_n4_b5_v19_s3_p1\\}",
          "id": "p2_n4_b5_v19_s3_p1"
        }
      ],
      "endingText": null
    },
    {
      "title": "\\{p2_n4_b5_v19_s4\\}",
      "id": "p2_n4_b5_v19_s4",
      "paragraphs": [
        {
          "number": "184",
          "content": "\\{p2_n4_b5_v19_s4_p1\\}",
          "id": "p2_n4_b5_v19_s4_p1"
        }
      ],
      "endingText": null
    },
    {
      "title": "\\{p2_n4_b5_v19_s5\\}",
      "id": "p2_n4_b5_v19_s5",
      "paragraphs": [
        {
          "number": "185",
          "content": "\\{p2_n4_b5_v19_s5_p1\\}",
          "id": "p2_n4_b5_v19_s5_p1"
        }
      ],
      "endingText": null
    },
    {
      "title": "\\{p2_n4_b5_v19_s6\\}",
      "id": "p2_n4_b5_v19_s6",
      "paragraphs": [
        {
          "number": "186",
          "content": "\\{p2_n4_b5_v19_s6_p1\\}",
          "id": "p2_n4_b5_v19_s6_p1"
        }
      ],
      "endingText": null
    },
    {
      "title": "\\{p2_n4_b5_v19_s7\\}",
      "id": "p2_n4_b5_v19_s7",
      "paragraphs": [
        {
          "number": "187",
          "content": "\\{p2_n4_b5_v19_s7_p1\\}",
          "id": "p2_n4_b5_v19_s7_p1"
        }
      ],
      "endingText": null
    },
    {
      "title": "\\{p2_n4_b5_v19_s8\\}",
      "id": "p2_n4_b5_v19_s8",
      "paragraphs": [
        {
          "number": "188",
          "content": "\\{p2_n4_b5_v19_s8_p1\\}",
          "id": "p2_n4_b5_v19_s8_p1"
        }
      ],
      "endingText": null
    },
    {
      "title": "\\{p2_n4_b5_v19_s9\\}",
      "id": "p2_n4_b5_v19_s9",
      "paragraphs": [
        {
          "number": "189",
          "content": "\\{p2_n4_b5_v19_s9_p1\\}",
          "id": "p2_n4_b5_v19_s9_p1"
        }
      ],
      "endingText": null
    },
    {
      "title": "\\{p2_n4_b5_v19_s10\\}",
      "id": "p2_n4_b5_v19_s10",
      "paragraphs": [
        {
          "number": "190",
          "content": "\\{p2_n4_b5_v19_s10_p1\\}",
          "id": "p2_n4_b5_v19_s10_p1"
        }
      ],
      "endingText": null
    }
  ],
  "ending": "\\{p2_n4_b5_v19_e\\}"
}
